TermuxCustomBanner/__init__.py
TermuxCustomBanner/__main__.py
TermuxCustomBanner/banner_generator.py
TermuxCustomBanner/colors.py
TermuxCustomBanner-1.0.1.dist-info/LICENSE
TermuxCustomBanner-1.0.1.dist-info/METADATA
TermuxCustomBanner-1.0.1.dist-info/WHEEL
TermuxCustomBanner-1.0.1.dist-info/top_level.txt
TermuxCustomBanner-1.0.1.dist-info/RECORD
