Metadata-Version: 2.1
Name: TermuxCustomBanner
Version: 1.0.1
Summary: Creates custom banner for termux
Home-page: UNKNOWN
License: MIT License
Platform: UNKNOWN
Requires-Dist: pyfiglet
